setup.py
auth_base_template/__init__.py
auth_base_template/context_processors.py
auth_base_template/models.py
auth_base_template/tests.py
django_auth_base_template.egg-info/PKG-INFO
django_auth_base_template.egg-info/SOURCES.txt
django_auth_base_template.egg-info/dependency_links.txt
django_auth_base_template.egg-info/top_level.txt