Metadata-Version: 1.0
Name: django-auth-base-template
Version: 1.0.0
Summary: Switchable logged in/logged out base templates for Django
Home-page: http://github.com/dabapps/django-auth-base-template/
Author: Jamie Matthews
Author-email: jamie@dabapps.com
License: BSD
Platform: UNKNOWN
